Metadata-Version: 2.1
Name: pywaf
Version: 1.0.0
Summary: Atomic functions and wavelets
Author-email: tru17v@gmail.com
